{
  "title": "algebra-2 - Quiz 34",
  "description": "Full-length exam simulation for algebra-2 covering key concepts and problem-solving skills.",
  "duration": "60 minutes",
  "passingScore": 70,
  "questions": [
    {
      "question": "Sample question 1 for algebra-2. This quiz is currently being developed.",
      "options": [
        "Option A",
        "Option B", 
        "Option C",
        "Option D"
      ],
      "correct": 0,
      "explanation": "This is a placeholder explanation. Real content coming soon!",
      "points": 1
    },
    {
      "question": "Sample question 2 for algebra-2. Check back later for actual exam content.",
      "options": [
        "Option A",
        "Option B",
        "Option C", 
        "Option D"
      ],
      "correct": 1,
      "explanation": "Detailed explanations will be provided when the quiz is fully developed.",
      "points": 1
    }
  ]
}
